pydownsampler/__init__.py
pydownsampler/pydownsampler.py
pydownsampler-1.0.dist-info/LICENSE
pydownsampler-1.0.dist-info/METADATA
pydownsampler-1.0.dist-info/WHEEL
pydownsampler-1.0.dist-info/entry_points.txt
pydownsampler-1.0.dist-info/top_level.txt
pydownsampler-1.0.dist-info/RECORD
